sleamdge/__init__.py
sleamdge/__main__.py
sleamdge/client.py
sleamdge/command.py
sleamdge/config.py
sleamdge/contact.py
sleamdge/gateway.py
sleamdge/group.py
sleamdge/session.py
sleamdge/types.py
sleamdge/util.py
sleamdge-0.3.0.dist-info/licenses/LICENSE
sleamdge-0.3.0.dist-info/METADATA
sleamdge-0.3.0.dist-info/WHEEL
sleamdge-0.3.0.dist-info/entry_points.txt
sleamdge-0.3.0.dist-info/top_level.txt
sleamdge-0.3.0.dist-info/RECORD
