Metadata-Version: 2.4
Name: sleamdge
Version: 0.3.0
Summary: A Steam/XMPP gateway
Author-email: Nicolas Cedilnik <nicoco@nicoco.fr>
License-Expression: AGPL-3.0-or-later
Project-URL: Homepage, https://codeberg.org/slidge/sleamdge
Project-URL: Issues, https://codeberg.org/slidge/sleamdge/issues
Project-URL: Repository, https://codeberg.org/slidge/sleamdge
Project-URL: Chat room, https://slidge.im/xmpp-web/#/guest?join=slidge@conference.nicoco.fr
Project-URL: Documentation, https://slidge.im/docs/sleamdge/main
Project-URL: changelog, https://codeberg.org/slidge/sleamdge/releases
Keywords: xmpp,gateway,bridge,instant messaging,chat,steam
Classifier: Topic :: Internet :: XMPP
Requires-Python: >=3.11
License-File: LICENSE
Requires-Dist: steamio<2,>=1.1
Requires-Dist: slidge<0.4,>=0.3.0beta
Dynamic: license-file
